set_test.v
module SET(clk, rst, en, central, radius, mode, busy, valid, candidate);
input clk;
input rst;
input en;
input [23:0] central;
input [11:0] radius;
input [1:0] mode;
output busy;
output valid;
output [7:0] candidate;

parameter STATE_INPUT = 2'd0;
parameter STATE_CAL = 2'd1;
parameter STATE_OUTPUT = 2'd2;
parameter STATE_IDEL = 2'd3;

reg busy, valid;
reg [7:0] candidate;

reg [1:0] state, next_state;
reg [3:0] x_side, y_side;

reg [23:0] central_reg;
reg [11:0] radius_reg;
reg [1:0] mode_reg;

reg [3:0] x_side_a, x_side_b, x_side_c;
reg [3:0] y_side_a, y_side_b, y_side_c;
reg [8:0] circle_a, circle_b, circle_c;
reg [7:0] radius_a, radius_b, radius_c;

reg cal_valid;

// FSM

always @(posedge clk or posedge rst) begin
	if(rst) begin
		state <= STATE_INPUT;
	end
	else begin
		state <= next_state;
	end
end 

always @(*) begin
	case(state)
		STATE_INPUT: begin
			if(en)
				next_state = STATE_CAL;
			else
				next_state = STATE_INPUT;
		end
		STATE_CAL: begin
			if(x_side == 4'd8 && y_side == 4'd8)
				next_state = STATE_OUTPUT;
			else
				next_state = STATE_CAL;
		end
		STATE_OUTPUT: begin
			next_state = STATE_INPUT;
		end
		STATE_IDEL: begin
			next_state = STATE_IDEL;
		end
		default: next_state = STATE_IDEL;
	endcase
end

always @(*) begin
	if(central_reg[23:20] >= x_side) begin
		x_side_a = central_reg[23:20] - x_side;
	end
	else begin
		x_side_a = x_side - central_reg[23:20];
	end

	if(central_reg[19:16] >= y_side) begin
		y_side_a = central_reg[19:16] - y_side;
	end
	else begin
		y_side_a = y_side - central_reg[19:16];
	end

	if(central_reg[15:12] >= x_side) begin
		x_side_b = central_reg[15:12] - x_side;
	end
	else begin
		x_side_b = x_side - central_reg[15:12];
	end

	if(central_reg[11:8] >= y_side) begin
		y_side_b = central_reg[11:8] - y_side;
	end
	else begin
		y_side_b = y_side - central_reg[11:8];
	end

	if(central_reg[7:4] >= x_side) begin
		x_side_c = central_reg[7:4] - x_side;
	end
	else begin
		x_side_c = x_side - central_reg[7:4];
	end

	if(central_reg[3:0] >= y_side) begin
		y_side_c = central_reg[3:0] - y_side;
	end
	else begin
		y_side_c = y_side - central_reg[3:0];
	end
end

always @(*) begin
	circle_a = (x_side_a * x_side_a) + (y_side_a * y_side_a);
	circle_b = (x_side_b * x_side_b) + (y_side_b * y_side_b);
	circle_c = (x_side_c * x_side_c) + (y_side_c * y_side_c);

	radius_a = radius_reg[11:8] * radius_reg[11:8];
	radius_b = radius_reg[7:4] * radius_reg[7:4];
	radius_c = radius_reg[3:0] * radius_reg[3:0];
end

always @(*) begin
	case(mode_reg)
		2'd0: begin
			if((circle_a <= radius_a) == 1'b1)
				cal_valid = 1'b1;
			else
				cal_valid = 1'b0;
		end
		2'd1: begin
			if(((circle_a <= radius_a) & (circle_b <= radius_b)) == 1'b1)
				cal_valid = 1'b1;
			else
				cal_valid = 1'b0;
		end
		2'd2: begin
			if(((circle_a <= radius_a) ^ (circle_b <= radius_b)) == 1'b1)
				cal_valid = 1'b1;
			else
				cal_valid = 1'b0;
		end
		2'd3: begin
			if((~((circle_a <= radius_a) ^ (circle_b <= radius_b) ^ (circle_c <= radius_c))) & ((circle_a <= radius_a) | (circle_b <= radius_b) | (circle_c <= radius_c)) == 1'b1)
				cal_valid = 1'b1;
			else
			 	cal_valid = 1'b0;
		end
		default: cal_valid = 1'b0;
	endcase
end 

always @(posedge clk or posedge rst) begin
	if(rst) begin
		busy <= 1'b0;
		valid <= 1'b0;
		candidate <= 8'd0;
		x_side <= 4'd1;
		y_side <= 4'd1;
	end
	else begin
		case(state)
			STATE_INPUT: begin
				if(en) begin
					central_reg <= central;
					radius_reg <= radius;
					mode_reg <= mode;
					busy <= 1'b0;
					candidate <= 8'd0;
				end
				else begin
					busy <= 1'b0;
					valid <= 1'b0;
				end
			end
			STATE_CAL: begin
				if(x_side == 4'd8 && y_side == 4'd8) begin
					x_side <= 4'd1;
					y_side <= 4'd1;
				end
				else begin
					if(x_side == 4'd8) begin
						y_side <= y_side + 4'd1;
						x_side <= 4'd1;
					end
					else begin
						x_side <= x_side + 4'd1;
					end
				end
				if(cal_valid)
					candidate <= candidate + 1;
			end
			STATE_OUTPUT: begin
				valid <= 1'b1;
			end
		endcase
	end
end

endmodule

testfixture.v
`timescale 1ns/10ps
`define SDFFILE    "set_dc.sdf"    // Modify your sdf file name here
`define cycle 10.0
`define terminate_cycle 200000 // Modify your terminate ycle here


module testfixture1;

`define central_pattern "./dat/Central_pattern.dat"
`define radius_pattern "./dat/Radius_pattern.dat"
`define  candidate_result_Length "./dat/candidate_result_Length.dat"
`define  candidate_united_result_Length "./dat/candidate_united_result_Length.dat"
`define  candidate_diff_result_Length "./dat/candidate_diff_result_Length.dat"
`define  candidate_intersect_result_Length "./dat/candidate_intersect_result_Length.dat"

reg clk = 0;
reg rst;
reg en;
reg [23:0] central;
reg [11:0] radius;
reg [1:0] mode;
wire busy;
wire valid;
wire [7:0] candidate;

integer err_cnt;

reg [23:0] central_pat_mem [0:63];
reg [11:0] radius_pat_mem[0:63];
reg [7:0] expected_mem [0:63];

`ifdef SDF
initial $sdf_annotate(`SDFFILE, u_set);
`endif

initial begin
	$dumpfile("set_test.vcd");
	$dumpvars;
end

initial begin
	$timeformat(-9, 1, " ns", 9); //Display time in nanoseconds
	$readmemh(`central_pattern, central_pat_mem);
	$readmemh(`radius_pattern, radius_pat_mem);
//`ifdef MD1
//	$display("--------------------------- [ Function 1. Simulation START !! ] ---------------------------");
//	$readmemh(`candidate_result_Length, expected_mem);
//`elsif MD2
	$display("--------------------------- [ Function 2. Simulation START !! ] ---------------------------");
	$readmemh(`candidate_united_result_Length, expected_mem);
/*`elsif MD3
	$display("--------------------------- [ Function 3. Simulation START !! ] ---------------------------");
	$readmemh(`candidate_diff_result_Length, expected_mem);
`elsif MD4
	$display("--------------------------- [ Function 4. Simulation START !! ] ---------------------------");
	$readmemh(`candidate_intersect_result_Length, expected_mem);
`else
	$display("============================================================================");
	$display("|                                                                          |");
	$display("|  Please select one testbench for test !!                                 |");
	$display("|  Simulation can't be initialized !!                                      |");
	$display("|                                                                          |");
	$display("============================================================================");
	#1 $finish;
`endif
*/
end



always #(`cycle/2) clk = ~clk;




initial begin
//`ifdef MD1
	//mode = 2'b00;
//`elsif MD2
	mode = 2'b01;
/*`elsif MD3
	mode = 2'b10;
`elsif MD4
	mode = 2'b11;
`else
	mode = 2'bx;
`endif*/
end

SET u_set( .clk(clk), .rst(rst), .en(en), .central(central), .radius(radius), .mode(mode), .busy(busy), .valid(valid), .candidate(candidate) );

integer k;
integer p;
initial begin
	en = 0;
      	rst = 0;
	err_cnt = 0;
# `cycle;     
	rst = 1;
#(`cycle*3);
	rst = 0;
for (k = 0; k<=63; k = k+1) begin
	@(negedge clk);
	//change inputs at strobe point
        #(`cycle/4)	wait(busy == 0);
			en = 1;
			central = central_pat_mem[k];                
      			radius = radius_pat_mem[k];
			#(`cycle) en = 0;
			wait (valid == 1);
          	//Wait for signal output
          	@(negedge clk);
				if (candidate === expected_mem[k])
					$display(" Pattern %d at Mode %d is PASS !", k, mode);
				else begin
					$display(" Pattern %d at Mode %d is FAIL !. Expected candidate = %d, but the Response candidate = %d !! ", k, mode, expected_mem[k], candidate);
					err_cnt = err_cnt + 1;
				end
end
#(`cycle*2); 
     $display("--------------------------- Simulation FINISH !!---------------------------");
     if (err_cnt) begin 
     	$display("============================================================================");
     	$display("\n (T_T) FAIL!! The simulation result is FAIL!!! there were %d errors at all.\n", err_cnt);
	$display("============================================================================");
	end
     else begin 
     	$display("============================================================================");
	$display("\n \\(^o^)/ CONGRATULATIONS!!  The simulation result is PASS!!!\n");
	$display("============================================================================");
	end
$finish;
end


always@(err_cnt) begin
	if (err_cnt == 10) begin
	$display("============================================================================");
     	$display("\n (>_<) FAIL!! The simulation FAIL result is too many ! Please check your code @@ \n");
	$display("============================================================================");
	$finish;
	end
end

initial begin 
	#`terminate_cycle;
	$display("================================================================================================================");
	$display("--------------------------- (/`n`)/ ~#  There was something wrong with your code !! ---------------------------"); 
	$display("--------------------------- The simulation can't finished!!, Please check it !!! ---------------------------"); 
	$display("================================================================================================================");
	$finish;
end


endmodule

set_test.vcd
$date
	Tue Sep 12 17:42:24 2017
$end
$version
	Icarus Verilog
$end
$timescale
	10ps
$end
$scope module testfixture1 $end
$var wire 1 ! valid $end
$var wire 8 " candidate [7:0] $end
$var wire 1 # busy $end
$var reg 24 $ central [23:0] $end
$var reg 1 % clk $end
$var reg 1 & en $end
$var reg 2 ' mode [1:0] $end
$var reg 12 ( radius [11:0] $end
$var reg 1 ) rst $end
$var integer 32 * err_cnt [31:0] $end
$var integer 32 + k [31:0] $end
$scope module u_set $end
$var wire 24 , central [23:0] $end
$var wire 1 % clk $end
$var wire 1 & en $end
$var wire 2 - mode [1:0] $end
$var wire 12 . radius [11:0] $end
$var wire 1 ) rst $end
$var reg 1 # busy $end
$var reg 1 / cal_valid $end
$var reg 8 0 candidate [7:0] $end
$var reg 24 1 central_reg [23:0] $end
$var reg 9 2 circle_a [8:0] $end
$var reg 9 3 circle_b [8:0] $end
$var reg 9 4 circle_c [8:0] $end
$var reg 2 5 mode_reg [1:0] $end
$var reg 2 6 next_state [1:0] $end
$var reg 8 7 radius_a [7:0] $end
$var reg 8 8 radius_b [7:0] $end
$var reg 8 9 radius_c [7:0] $end
$var reg 12 : radius_reg [11:0] $end
$var reg 2 ; state [1:0] $end
$var reg 1 ! valid $end
$var reg 4 < x_side [3:0] $end
$var reg 4 = x_side_a [3:0] $end
$var reg 4 > x_side_b [3:0] $end
$var reg 4 ? x_side_c [3:0] $end
$var reg 4 @ y_side [3:0] $end
$var reg 4 A y_side_a [3:0] $end
$var reg 4 B y_side_b [3:0] $end
$var reg 4 C y_side_c [3:0] $end
$upscope $end
$upscope $end
$enddefinitions $end
#0
$dumpvars
bx C
bx B
bx A
bx @
bx ?
bx >
bx =
bx <
bx ;
bx :
bx 9
bx 8
bx 7
b11 6
bx 5
bx 4
bx 3
bx 2
bx 1
bx 0
x/
bx .
b1 -
bx ,
bx +
b0 *
0)
bx (
b1 '
0&
0%
bx $
x#
bx "
x!
$end
#500
b11 ;
1%
#1000
b0 6
b1 @
b1 <
b0 "
b0 0
0!
0#
b0 ;
0%
1)
#1500
1%
#2000
0%
#2500
1%
#3000
0%
#3500
1%
#4000
0%
b0 +
0)
#4250
b1 6
b1100110010 (
b1100110010 .
b10101010011001101100010 $
b10101010011001101100010 ,
1&
#4500
0/
b100 9
b1001 8
b1001 7
b11010 4
b1000 3
b100000 2
b1 C
b101 ?
b10 B
b10 >
b100 A
b100 =
b1 5
b1100110010 :
b10101010011001101100010 1
b1 ;
1%
#5000
0%
#5250
0&
#5500
b10001 4
b101 3
b11001 2
b100 ?
b1 >
b11 =
b10 <
1%
#6000
0%
#6500
b1010 4
b100 3
b10100 2
b11 ?
b0 >
b10 =
b11 <
1%
#7000
0%
#7500
b101 4
b101 3
b10001 2
b10 ?
b1 >
b1 =
b100 <
1%
#8000
0%
#8500
b10 4
b1000 3
b10000 2
b1 ?
b10 >
b0 =
b101 <
1%
#9000
0%
#9500
b1 4
b1101 3
b10001 2
b0 ?
b11 >
b1 =
b110 <
1%
#10000
0%
#10500
b10 4
b10100 3
b10100 2
b1 ?
b100 >
b10 =
b111 <
1%
#11000
0%
#11500
b101 4
b11101 3
b11001 2
b10 ?
b101 >
b11 =
b1000 <
1%
#12000
0%
#12500
b11001 4
b101 3
b0 C
b101 ?
b1 B
b10 >
b11 A
b100 =
b1 <
b10 @
1%
#13000
0%
#13500
b10000 4
b10 3
b10010 2
b100 ?
b1 >
b11 =
b10 <
1%
#14000
0%
#14500
b1001 4
b1 3
b1101 2
b11 ?
b0 >
b10 =
b11 <
1%
#15000
0%
#15500
b100 4
b10 3
b1010 2
b10 ?
b1 >
b1 =
b100 <
1%
#16000
0%
#16500
1/
b1 4
b101 3
b1001 2
b1 ?
b10 >
b0 =
b101 <
1%
#17000
0%
#17500
0/
b0 4
b1010 3
b1010 2
b0 ?
b11 >
b1 =
b1 "
b1 0
b110 <
1%
#18000
0%
#18500
b1 4
b10001 3
b1101 2
b1 ?
b100 >
b10 =
b111 <
1%
#19000
0%
#19500
b100 4
b11010 3
b10010 2
b10 ?
b101 >
b11 =
b1000 <
1%
#20000
0%
#20500
b11010 4
b100 3
b10100 2
b1 C
b101 ?
b0 B
b10 >
b10 A
b100 =
b1 <
b11 @
1%
#21000
0%
#21500
b10001 4
b1 3
b1101 2
b100 ?
b1 >
b11 =
b10 <
1%
#22000
0%
#22500
1/
b1010 4
b0 3
b1000 2
b11 ?
b0 >
b10 =
b11 <
1%
#23000
0%
#23500
b101 4
b1 3
b101 2
b10 ?
b1 >
b1 =
b10 "
b10 0
b100 <
1%
#24000
0%
#24500
b10 4
b100 3
b100 2
b1 ?
b10 >
b0 =
b11 "
b11 0
b101 <
1%
#25000
0%
#25500
b1 4
b1001 3
b101 2
b0 ?
b11 >
b1 =
b100 "
b100 0
b110 <
1%
#26000
0%
#26500
0/
b10 4
b10000 3
b1000 2
b1 ?
b100 >
b10 =
b101 "
b101 0
b111 <
1%
#27000
0%
#27500
b101 4
b11001 3
b1101 2
b10 ?
b101 >
b11 =
b1000 <
1%
#28000
0%
#28500
b11101 4
b101 3
b10001 2
b10 C
b101 ?
b1 B
b10 >
b1 A
b100 =
b1 <
b100 @
1%
#29000
0%
#29500
b10100 4
b10 3
b1010 2
b100 ?
b1 >
b11 =
b10 <
1%
#30000
0%
#30500
1/
b1101 4
b1 3
b101 2
b11 ?
b0 >
b10 =
b11 <
1%
#31000
0%
#31500
b1000 4
b10 3
b10 2
b10 ?
b1 >
b1 =
b110 "
b110 0
b100 <
1%
#32000
0%
#32500
b101 4
b101 3
b1 2
b1 ?
b10 >
b0 =
b111 "
b111 0
b101 <
1%
#33000
0%
#33500
0/
b100 4
b1010 3
b10 2
b0 ?
b11 >
b1 =
b1000 "
b1000 0
b110 <
1%
#34000
0%
#34500
b101 4
b10001 3
b101 2
b1 ?
b100 >
b10 =
b111 <
1%
#35000
0%
#35500
b1000 4
b11010 3
b1010 2
b10 ?
b101 >
b11 =
b1000 <
1%
#36000
0%
#36500
b100010 4
b1000 3
b10000 2
b11 C
b101 ?
b10 B
b10 >
b0 A
b100 =
b1 <
b101 @
1%
#37000
0%
#37500
1/
b11001 4
b101 3
b1001 2
b100 ?
b1 >
b11 =
b10 <
1%
#38000
0%
#38500
b10010 4
b100 3
b100 2
b11 ?
b0 >
b10 =
b1001 "
b1001 0
b11 <
1%
#39000
0%
#39500
b1101 4
b101 3
b1 2
b10 ?
b1 >
b1 =
b1010 "
b1010 0
b100 <
1%
#40000
0%
#40500
b1010 4
b1000 3
b0 2
b1 ?
b10 >
b0 =
b1011 "
b1011 0
b101 <
1%
#41000
0%
#41500
0/
b1001 4
b1101 3
b1 2
b0 ?
b11 >
b1 =
b1100 "
b1100 0
b110 <
1%
#42000
0%
#42500
b1010 4
b10100 3
b100 2
b1 ?
b100 >
b10 =
b111 <
1%
#43000
0%
#43500
b1101 4
b11101 3
b1001 2
b10 ?
b101 >
b11 =
b1000 <
1%
#44000
0%
#44500
b101001 4
b1101 3
b10001 2
b100 C
b101 ?
b11 B
b10 >
b1 A
b100 =
b1 <
b110 @
1%
#45000
0%
#45500
b100000 4
b1010 3
b1010 2
b100 ?
b1 >
b11 =
b10 <
1%
#46000
0%
#46500
1/
b11001 4
b1001 3
b101 2
b11 ?
b0 >
b10 =
b11 <
1%
#47000
0%
#47500
0/
b10100 4
b1010 3
b10 2
b10 ?
b1 >
b1 =
b1101 "
b1101 0
b100 <
1%
#48000
0%
#48500
b10001 4
b1101 3
b1 2
b1 ?
b10 >
b0 =
b101 <
1%
#49000
0%
#49500
b10000 4
b10010 3
b10 2
b0 ?
b11 >
b1 =
b110 <
1%
#50000
0%
#50500
b10001 4
b11001 3
b101 2
b1 ?
b100 >
b10 =
b111 <
1%
#51000
0%
#51500
b10100 4
b100010 3
b1010 2
b10 ?
b101 >
b11 =
b1000 <
1%
#52000
0%
#52500
b110010 4
b10100 3
b10100 2
b101 C
b101 ?
b100 B
b10 >
b10 A
b100 =
b1 <
b111 @
1%
#53000
0%
#53500
b101001 4
b10001 3
b1101 2
b100 ?
b1 >
b11 =
b10 <
1%
#54000
0%
#54500
b100010 4
b10000 3
b1000 2
b11 ?
b0 >
b10 =
b11 <
1%
#55000
0%
#55500
b11101 4
b10001 3
b101 2
b10 ?
b1 >
b1 =
b100 <
1%
#56000
0%
#56500
b11010 4
b10100 3
b100 2
b1 ?
b10 >
b0 =
b101 <
1%
#57000
0%
#57500
b11001 4
b11001 3
b101 2
b0 ?
b11 >
b1 =
b110 <
1%
#58000
0%
#58500
b11010 4
b100000 3
b1000 2
b1 ?
b100 >
b10 =
b111 <
1%
#59000
0%
#59500
b11101 4
b101001 3
b1101 2
b10 ?
b101 >
b11 =
b1000 <
1%
#60000
0%
#60500
b111101 4
b11101 3
b11001 2
b110 C
b101 ?
b101 B
b10 >
b11 A
b100 =
b1 <
b1000 @
1%
#61000
0%
#61500
b110100 4
b11010 3
b10010 2
b100 ?
b1 >
b11 =
b10 <
1%
#62000
0%
#62500
b101101 4
b11001 3
b1101 2
b11 ?
b0 >
b10 =
b11 <
1%
#63000
0%
#63500
b101000 4
b11010 3
b1010 2
b10 ?
b1 >
b1 =
b100 <
1%
#64000
0%
#64500
b100101 4
b11101 3
b1001 2
b1 ?
b10 >
b0 =
b101 <
1%
#65000
0%
#65500
b100100 4
b100010 3
b1010 2
b0 ?
b11 >
b1 =
b110 <
1%
#66000
0%
#66500
b100101 4
b101001 3
b1101 2
b1 ?
b100 >
b10 =
b111 <
1%
#67000
0%
#67500
b101000 4
b110010 3
b10010 2
b10 ?
b101 >
b11 =
b10 6
b1000 <
1%
#68000
0%
#68500
b11010 4
b1000 3
b100000 2
b1 C
b101 ?
b10 B
b10 >
b100 A
b100 =
b0 6
b1 @
b1 <
b10 ;
1%
#69000
0%
#69500
b0 ;
1!
1%
#70000
b1 +
0%
#70500
0!
1%
#71000
0%
#71250
b1 6
b1000100011 (
b1000100011 .
b10001100010010001010011 $
b10001100010010001010011 ,
1&
#71500
b1001 9
b100 8
b100 7
b10100 4
b1010 3
b100010 2
b10 C
b100 ?
b11 B
b1 >
b101 A
b11 =
b1 ;
b0 "
b0 0
b1000100011 :
b10001100010010001010011 1
1%
#72000
0%
#72250
0&
#72500
b1101 4
b1001 3
b11101 2
b11 ?
b0 >
b10 =
b10 <
1%
#73000
0%
#73500
b1000 4
b1010 3
b11010 2
b10 ?
b1 >
b1 =
b11 <
1%
#74000
0%
#74500
b101 4
b1101 3
b11001 2
b1 ?
b10 >
b0 =
b100 <
1%
#75000
0%
#75500
b100 4
b10010 3
b11010 2
b0 ?
b11 >
b1 =
b101 <
1%
#76000
0%
#76500
b101 4
b11001 3
b11101 2
b1 ?
b100 >
b10 =
b110 <
1%
#77000
0%
#77500
b1000 4
b100010 3
b100010 2
b10 ?
b101 >
b11 =
b111 <
1%
#78000
0%
#78500
b1101 4
b101101 3
b101001 2
b11 ?
b110 >
b100 =
b1000 <
1%
#79000
0%
#79500
b10001 4
b101 3
b11001 2
b1 C
b100 ?
b10 B
b1 >
b100 A
b11 =
b1 <
b10 @
1%
#80000
0%
#80500
b1010 4
b100 3
b10100 2
b11 ?
b0 >
b10 =
b10 <
1%
#81000
0%
#81500
b101 4
b101 3
b10001 2
b10 ?
b1 >
b1 =
b11 <
1%
#82000
0%
#82500
b10 4
b1000 3
b10000 2
b1 ?
b10 >
b0 =
b100 <
1%
#83000
0%
#83500
b1 4
b1101 3
b10001 2
b0 ?
b11 >
b1 =
b101 <
1%
#84000
0%
#84500
b10 4
b10100 3
b10100 2
b1 ?
b100 >
b10 =
b110 <
1%
#85000
0%
#85500
b101 4
b11101 3
b11001 2
b10 ?
b101 >
b11 =
b111 <
1%
#86000
0%
#86500
b1010 4
b101000 3
b100000 2
b11 ?
b110 >
b100 =
b1000 <
1%
#87000
0%
#87500
b10000 4
b10 3
b10010 2
b0 C
b100 ?
b1 B
b1 >
b11 A
b11 =
b1 <
b11 @
1%
#88000
0%
#88500
b1001 4
b1 3
b1101 2
b11 ?
b0 >
b10 =
b10 <
1%
#89000
0%
#89500
b100 4
b10 3
b1010 2
b10 ?
b1 >
b1 =
b11 <
1%
#90000
0%
#90500
b1 4
b101 3
b1001 2
b1 ?
b10 >
b0 =
b100 <
1%
#91000
0%
#91500
b0 4
b1010 3
b1010 2
b0 ?
b11 >
b1 =
b101 <
1%
#92000
0%
#92500
b1 4
b10001 3
b1101 2
b1 ?
b100 >
b10 =
b110 <
1%
#93000
0%
#93500
b100 4
b11010 3
b10010 2
b10 ?
b101 >
b11 =
b111 <
1%
#94000
0%
#94500
b1001 4
b100101 3
b11001 2
b11 ?
b110 >
b100 =
b1000 <
1%
#95000
0%
#95500
b10001 4
b1 3
b1101 2
b1 C
b100 ?
b0 B
b1 >
b10 A
b11 =
b1 <
b100 @
1%
#96000
0%
#96500
b1010 4
b0 3
b1000 2
b11 ?
b0 >
b10 =
b10 <
1%
#97000
0%
#97500
b101 4
b1 3
b101 2
b10 ?
b1 >
b1 =
b11 <
1%
#98000
0%
#98500
1/
b10 4
b100 3
b100 2
b1 ?
b10 >
b0 =
b100 <
1%
#99000
0%
#99500
0/
b1 4
b1001 3
b101 2
b0 ?
b11 >
b1 =
b1 "
b1 0
b101 <
1%
#100000
0%
#100500
b10 4
b10000 3
b1000 2
b1 ?
b100 >
b10 =
b110 <
1%
#101000
0%
#101500
b101 4
b11001 3
b1101 2
b10 ?
b101 >
b11 =
b111 <
1%
#102000
0%
#102500
b1010 4
b100100 3
b10100 2
b11 ?
b110 >
b100 =
b1000 <
1%
#103000
0%
#103500
b10100 4
b10 3
b1010 2
b10 C
b100 ?
b1 B
b1 >
b1 A
b11 =
b1 <
b101 @
1%
#104000
0%
#104500
b1101 4
b1 3
b101 2
b11 ?
b0 >
b10 =
b10 <
1%
#105000
0%
#105500
1/
b1000 4
b10 3
b10 2
b10 ?
b1 >
b1 =
b11 <
1%
#106000
0%
#106500
0/
b101 4
b101 3
b1 2
b1 ?
b10 >
b0 =
b10 "
b10 0
b100 <
1%
#107000
0%
#107500
b100 4
b1010 3
b10 2
b0 ?
b11 >
b1 =
b101 <
1%
#108000
0%
#108500
b101 4
b10001 3
b101 2
b1 ?
b100 >
b10 =
b110 <
1%
#109000
0%
#109500
b1000 4
b11010 3
b1010 2
b10 ?
b101 >
b11 =
b111 <
1%
#110000
0%
#110500
b1101 4
b100101 3
b10001 2
b11 ?
b110 >
b100 =
b1000 <
1%
#111000
0%
#111500
b11001 4
b101 3
b1001 2
b11 C
b100 ?
b10 B
b1 >
b0 A
b11 =
b1 <
b110 @
1%
#112000
0%
#112500
1/
b10010 4
b100 3
b100 2
b11 ?
b0 >
b10 =
b10 <
1%
#113000
0%
#113500
0/
b1101 4
b101 3
b1 2
b10 ?
b1 >
b1 =
b11 "
b11 0
b11 <
1%
#114000
0%
#114500
b1010 4
b1000 3
b0 2
b1 ?
b10 >
b0 =
b100 <
1%
#115000
0%
#115500
b1001 4
b1101 3
b1 2
b0 ?
b11 >
b1 =
b101 <
1%
#116000
0%
#116500
b1010 4
b10100 3
b100 2
b1 ?
b100 >
b10 =
b110 <
1%
#117000
0%
#117500
b1101 4
b11101 3
b1001 2
b10 ?
b101 >
b11 =
b111 <
1%
#118000
0%
#118500
b10010 4
b101000 3
b10000 2
b11 ?
b110 >
b100 =
b1000 <
1%
#119000
0%
#119500
b100000 4
b1010 3
b1010 2
b100 C
b100 ?
b11 B
b1 >
b1 A
b11 =
b1 <
b111 @
1%
#120000
0%
#120500
b11001 4
b1001 3
b101 2
b11 ?
b0 >
b10 =
b10 <
1%
#121000
0%
#121500
b10100 4
b1010 3
b10 2
b10 ?
b1 >
b1 =
b11 <
1%
#122000
0%
#122500
b10001 4
b1101 3
b1 2
b1 ?
b10 >
b0 =
b100 <
1%
#123000
0%
#123500
b10000 4
b10010 3
b10 2
b0 ?
b11 >
b1 =
b101 <
1%
#124000
0%
#124500
b10001 4
b11001 3
b101 2
b1 ?
b100 >
b10 =
b110 <
1%
#125000
0%
#125500
b10100 4
b100010 3
b1010 2
b10 ?
b101 >
b11 =
b111 <
1%
#126000
0%
#126500
b11001 4
b101101 3
b10001 2
b11 ?
b110 >
b100 =
b1000 <
1%
#127000
0%
#127500
b101001 4
b10001 3
b1101 2
b101 C
b100 ?
b100 B
b1 >
b10 A
b11 =
b1 <
b1000 @
1%
#128000
0%
#128500
b100010 4
b10000 3
b1000 2
b11 ?
b0 >
b10 =
b10 <
1%
#129000
0%
#129500
b11101 4
b10001 3
b101 2
b10 ?
b1 >
b1 =
b11 <
1%
#130000
0%
#130500
b11010 4
b10100 3
b100 2
b1 ?
b10 >
b0 =
b100 <
1%
#131000
0%
#131500
b11001 4
b11001 3
b101 2
b0 ?
b11 >
b1 =
b101 <
1%
#132000
0%
#132500
b11010 4
b100000 3
b1000 2
b1 ?
b100 >
b10 =
b110 <
1%
#133000
0%
#133500
b11101 4
b101001 3
b1101 2
b10 ?
b101 >
b11 =
b111 <
1%
#134000
0%
#134500
b100010 4
b110100 3
b10100 2
b11 ?
b110 >
b100 =
b10 6
b1000 <
1%
#135000
0%
#135500
b10100 4
b1010 3
b100010 2
b10 C
b100 ?
b11 B
b1 >
b101 A
b11 =
b0 6
b10 ;
b1 @
b1 <
1%
#136000
0%
#136500
1!
b0 ;
1%
#137000
b10 +
0%
#137500
0!
1%
#138000
0%
#138250
b1 6
b11101100001011001000010 $
b11101100001011001000010 ,
1&
#138500
b1010 4
b11001 3
b111101 2
b1 C
b11 ?
b101 B
b0 >
b110 =
b0 "
b0 0
b11101100001011001000010 1
b1 ;
1%
#139000
0%
#139250
0&
#139500
b101 4
b11010 3
b110010 2
b10 ?
b1 >
b101 =
b10 <
1%
#140000
0%
#140500
b10 4
b11101 3
b101001 2
b1 ?
b10 >
b100 =
b11 <
1%
#141000
0%
#141500
b1 4
b100010 3
b100010 2
b0 ?
b11 >
b11 =
b100 <
1%
#142000
0%
#142500
b10 4
b101001 3
b11101 2
b1 ?
b100 >
b10 =
b101 <
1%
#143000
0%
#143500
b101 4
b110010 3
b11010 2
b10 ?
b101 >
b1 =
b110 <
1%
#144000
0%
#144500
b1010 4
b111101 3
b11001 2
b11 ?
b110 >
b0 =
b111 <
1%
#145000
0%
#145500
b10001 4
b1001010 3
b11010 2
b100 ?
b111 >
b1 =
b1000 <
1%
#146000
0%
#146500
b1001 4
b10000 3
b110100 2
b0 C
b11 ?
b100 B
b0 >
b100 A
b110 =
b1 <
b10 @
1%
#147000
0%
#147500
b100 4
b10001 3
b101001 2
b10 ?
b1 >
b101 =
b10 <
1%
#148000
0%
#148500
b1 4
b10100 3
b100000 2
b1 ?
b10 >
b100 =
b11 <
1%
#149000
0%
#149500
b0 4
b11001 3
b11001 2
b0 ?
b11 >
b11 =
b100 <
1%
#150000
0%
#150500
b1 4
b100000 3
b10100 2
b1 ?
b100 >
b10 =
b101 <
1%
#151000
0%
#151500
b100 4
b101001 3
b10001 2
b10 ?
b101 >
b1 =
b110 <
1%
#152000
0%
#152500
b1001 4
b110100 3
b10000 2
b11 ?
b110 >
b0 =
b111 <
1%
#153000
0%
#153500
b10000 4
b1000001 3
b10001 2
b100 ?
b111 >
b1 =
b1000 <
1%
#154000
0%
#154500
b1010 4
b1001 3
b101101 2
b1 C
b11 ?
b11 B
b0 >
b11 A
b110 =
b1 <
b11 @
1%
#155000
0%
#155500
b101 4
b1010 3
b100010 2
b10 ?
b1 >
b101 =
b10 <
1%
#156000
0%
#156500
b10 4
b1101 3
b11001 2
b1 ?
b10 >
b100 =
b11 <
1%
#157000
0%
#157500
b1 4
b10010 3
b10010 2
b0 ?
b11 >
b11 =
b100 <
1%
#158000
0%
#158500
b10 4
b11001 3
b1101 2
b1 ?
b100 >
b10 =
b101 <
1%
#159000
0%
#159500
b101 4
b100010 3
b1010 2
b10 ?
b101 >
b1 =
b110 <
1%
#160000
0%
#160500
b1010 4
b101101 3
b1001 2
b11 ?
b110 >
b0 =
b111 <
1%
#161000
0%
#161500
b10001 4
b111010 3
b1010 2
b100 ?
b111 >
b1 =
b1000 <
1%
#162000
0%
#162500
b1101 4
b100 3
b101000 2
b10 C
b11 ?
b10 B
b0 >
b10 A
b110 =
b1 <
b100 @
1%
#163000
0%
#163500
b1000 4
b101 3
b11101 2
b10 ?
b1 >
b101 =
b10 <
1%
#164000
0%
#164500
b101 4
b1000 3
b10100 2
b1 ?
b10 >
b100 =
b11 <
1%
#165000
0%
#165500
b100 4
b1101 3
b1101 2
b0 ?
b11 >
b11 =
b100 <
1%
#166000
0%
#166500
b101 4
b10100 3
b1000 2
b1 ?
b100 >
b10 =
b101 <
1%
#167000
0%
#167500
b1000 4
b11101 3
b101 2
b10 ?
b101 >
b1 =
b110 <
1%
#168000
0%
#168500
b1101 4
b101000 3
b100 2
b11 ?
b110 >
b0 =
b111 <
1%
#169000
0%
#169500
b10100 4
b110101 3
b101 2
b100 ?
b111 >
b1 =
b1000 <
1%
#170000
0%
#170500
b10010 4
b1 3
b100101 2
b11 C
b11 ?
b1 B
b0 >
b1 A
b110 =
b1 <
b101 @
1%
#171000
0%
#171500
b1101 4
b10 3
b11010 2
b10 ?
b1 >
b101 =
b10 <
1%
#172000
0%
#172500
b1010 4
b101 3
b10001 2
b1 ?
b10 >
b100 =
b11 <
1%
#173000
0%
